{"tables": [{"title": "115年06月15日 價格指數(臺灣證券交易所)", "fields": ["指數", "收盤指數", "漲跌(+/-)", "漲跌點數", "漲跌百分比(%)", "特殊處理註記"], "data": [["寶島股價指數", "50,658.61", "<p style ='color:red'>+</p>", "1,353.26", "2.74", ""], ["發行量加權股價指數", "45,396.99", "<p style ='color:red'>+</p>", "1,227.95", "2.78", ""], ["臺灣公司治理100指數", "28,242.33", "<p style ='color:red'>+</p>", "732.71", "2.66", ""], ["臺灣50指數", "42,059.16", "<p style ='color:red'>+</p>", "1,231.03", "3.02", ""], ["臺灣50權重上限30%指數", "35,413.97", "<p style ='color:red'>+</p>", "1,088.14", "3.17", ""], ["臺灣中型100指數", "36,043.38", "<p style ='color:red'>+</p>", "737.87", "2.09", ""], ["臺灣資訊科技指數", "88,555.30", "<p style ='color:red'>+</p>", "2,741.50", "3.19", ""], ["臺灣發達指數", "18,491.07", "<p style ='color:red'>+</p>", "224.39", "1.23", ""], ["臺灣高股息指數", "14,444.72", "<p style ='color:red'>+</p>", "262.26", "1.85", ""], ["臺灣就業99指數", "28,289.30", "<p style ='color:red'>+</p>", "926.79", "3.39", ""], ["臺灣高薪100指數", "21,795.57", "<p style ='color:red'>+</p>", "512.65", "2.41", ""], ["未含金融指數", "40,854.80", "<p style ='color:red'>+</p>", "1,105.88", "2.78", ""], ["未含電子指數", "22,889.64", "<p style ='color:red'>+</p>", "431.17", "1.92", ""], ["未含金融電子指數", "15,025.54", "<p style ='color:red'>+</p>", "192.43", "1.30", ""], ["小型股300指數", "14,462.27", "<p style ='color:red'>+</p>", "273.59", "1.93", ""], ["水泥窯製類指數", "664.17", "<p style ='color:red'>+</p>", "15.66", "2.41", ""], ["塑膠化工類指數", "839.43", "<p style ='color:red'>+</p>", "30.79", "3.81", ""], ["機電類指數", "16,131.21", "<p style ='color:red'>+</p>", "463.19", "2.96", ""], ["水泥類指數", "125.00", "<p style ='color:red'>+</p>", "1.19", "0.96", ""], ["食品類指數", "1,953.48", "<p style ='color:green'>-</p>", "5.95", "-0.30", ""], ["塑膠類指數", "230.98", "<p style ='color:red'>+</p>", "15.32", "7.10", ""], ["紡織纖維類指數", "485.69", "<p style ='color:red'>+</p>", "1.62", "0.33", ""], ["電機機械類指數", "551.02", "<p style ='color:red'>+</p>", "10.74", "1.99", ""], ["電器電纜類指數", "113.00", "<p style ='color:red'>+</p>", "4.33", "3.98", ""], ["化學生技醫療類指數", "149.83", "<p style ='color:red'>+</p>", "1.67", "1.13", ""], ["化學類指數", "197.37", "<p style ='color:red'>+</p>", "2.64", "1.36", ""], ["生技醫療類指數", "79.89", "<p style ='color:red'>+</p>", "0.79", "1.00", ""], ["玻璃陶瓷類指數", "158.25", "<p style ='color:red'>+</p>", "7.45", "4.94", ""], ["造紙類指數", "261.71", "<p style ='color:red'>+</p>", "1.35", "0.52", ""], ["鋼鐵類指數", "119.00", "<p style ='color:red'>+</p>", "0.57", "0.48", ""], ["橡膠類指數", "200.94", "<p style ='color:green'>-</p>", "0.97", "-0.48", ""], ["汽車類指數", "296.00", "<p style ='color:red'>+</p>", "5.16", "1.77", ""], ["電子工業類指數", "2,930.82", "<p style ='color:red'>+</p>", "84.49", "2.97", ""], ["半導體類指數", "1,538.77", "<p style ='color:red'>+</p>", "49.22", "3.30", ""], ["電腦及週邊設備類指數", "407.52", "<p style ='color:red'>+</p>", "0.94", "0.23", ""], ["光電類指數", "67.11", "<p style ='color:red'>+</p>", "3.39", "5.32", ""], ["通信網路類指數", "257.78", "<p style ='color:red'>+</p>", "5.09", "2.01", ""], ["電子零組件類指數", "983.92", "<p style ='color:red'>+</p>", "28.77", "3.01", ""], ["電子通路類指數", "377.04", "<p style ='color:red'>+</p>", "1.79", "0.48", ""], ["資訊服務類指數", "211.86", "<p style ='color:green'>-</p>", "0.68", "-0.32", ""], ["其他電子類指數", "295.65", "<p style ='color:red'>+</p>", "5.96", "2.06", ""], ["建材營造類指數", "481.58", "<p style ='color:red'>+</p>", "2.84", "0.59", ""], ["航運類指數", "190.18", "<p style ='color:red'>+</p>", "0.17", "0.09", ""], ["觀光餐旅類指數", "103.44", "<p style ='color:red'>+</p>", "0.07", "0.07", ""], ["金融保險類指數", "3,072.19", "<p style ='color:red'>+</p>", "82.38", "2.76", ""], ["貿易百貨類指數", "241.62", "<p style ='color:red'>+</p>", "1.28", "0.53", ""], ["油電燃氣類指數", "77.56", "<p style ='color:red'>+</p>", "0.43", "0.56", ""], ["綠能環保類指數", "135.59", "<p style ='color:red'>+</p>", "2.88", "2.17", ""], ["數位雲端類指數", "48.25", "<p style ='color:green'>-</p>", "3.09", "-6.02", ""], ["運動休閒類指數", "61.92", "<p style ='color:green'>-</p>", "2.58", "-4.00", ""], ["居家生活類指數", "96.08", "<p style ='color:green'>-</p>", "0.91", "-0.94", ""], ["其他類指數", "281.30", "<p style ='color:green'>-</p>", "1.67", "-0.59", ""], ["臺指日報酬兩倍指數", "221,266.92", "<p style ='color:red'>+</p>", "11,654.91", "5.56", ""], ["臺指反向一倍指數", "1,293.25", "<p style ='color:green'>-</p>", "36.98", "-2.78", ""], ["電子類兩倍槓桿指數", "379,159.31", "<p style ='color:red'>+</p>", "21,248.34", "5.94", ""], ["電子類反向指數", "786.69", "<p style ='color:green'>-</p>", "24.07", "-2.97", ""]], "hints": "單位：元、股"}, {"title": "價格指數(跨市場)", "fields": ["指數", "收盤指數", "漲跌(+/-)", "漲跌點數", "漲跌百分比(%)", "特殊處理註記"], "data": [["臺灣生技指數", "3,629.70", "<p style ='color:red'>+</p>", "28.08", "0.78", ""], ["臺灣中小型公司治理指數", "20,585.61", "<p style ='color:red'>+</p>", "83.11", "0.41", ""], ["臺灣IPO指數", "9,355.85", "<p style ='color:red'>+</p>", "103.01", "1.11", ""], ["智慧中立指數", "3,156.60", "<p style ='color:green'>-</p>", "9.38", "-0.30", ""], ["臺灣企業社會責任中小型指數", "16,941.17", "<p style ='color:red'>+</p>", "263.46", "1.58", ""], ["特選臺灣電動車代表指數", "21,445.57", "<p style ='color:red'>+</p>", "138.21", "0.65", ""], ["臺灣科技龍頭通訊指數", "25,422.03", "<p style ='color:red'>+</p>", "717.94", "2.91", ""], ["臺灣全市場指數", "15,851.24", "<p style ='color:red'>+</p>", "434.56", "2.82", ""], ["臺灣全市場半導體指數", "20,574.47", "<p style ='color:red'>+</p>", "774.62", "3.91", ""], ["臺灣智慧移動與電動車指數", "16,785.58", "<p style ='color:red'>+</p>", "627.58", "3.88", ""], ["特選小資高價30指數", "22,129.29", "<p style ='color:red'>+</p>", "606.81", "2.82", ""], ["特選臺灣綠能及電動車指數", "11,631.39", "<p style ='color:red'>+</p>", "234.32", "2.06", ""], ["特選臺灣智能車供應鏈聯盟指數", "18,250.91", "<p style ='color:red'>+</p>", "557.19", "3.15", ""], ["臺灣全市場半導體精選30指數", "16,068.79", "<p style ='color:red'>+</p>", "558.44", "3.60", ""], ["特選臺灣高股息30指數", "7,192.68", "<p style ='color:red'>+</p>", "117.76", "1.66", ""], ["臺灣友善環境指數", "13,225.54", "<p style ='color:red'>+</p>", "315.28", "2.44", ""], ["台灣永續價值指數", "13,263.46", "<p style ='color:red'>+</p>", "316.97", "2.45", ""], ["特選臺灣IC設計指數", "7,617.48", "<p style ='color:red'>+</p>", "239.79", "3.25", ""], ["特選臺灣環境永續高股息指數", "8,119.71", "<p style ='color:red'>+</p>", "112.55", "1.41", ""], ["臺灣友善環境50指數", "12,506.88", "<p style ='color:red'>+</p>", "358.65", "2.95", ""], ["特選臺灣IC設計產業代表指數", "10,150.69", "<p style ='color:red'>+</p>", "350.86", "3.58", ""], ["特選臺灣綠能指數", "9,913.83", "<p style ='color:red'>+</p>", "61.04", "0.62", ""], ["特選臺灣智慧50指數", "10,418.33", "<p style ='color:red'>+</p>", "239.31", "2.35", ""], ["臺灣晶圓製造指數", "16,946.91", "<p style ='color:red'>+</p>", "711.34", "4.38", ""], ["臺灣精選高息指數", "8,100.32", "<p style ='color:red'>+</p>", "119.22", "1.49", ""], ["臺灣多因子優選高股息30指數", "11,337.73", "<p style ='color:red'>+</p>", "255.04", "2.30", ""], ["特選臺灣優利高填息30指數", "11,612.69", "<p style ='color:red'>+</p>", "392.39", "3.50", ""], ["特選臺灣科技優息指數", "15,367.52", "<p style ='color:red'>+</p>", "478.86", "3.22", ""], ["臺灣半導體收益指數", "16,262.53", "<p style ='color:red'>+</p>", "462.31", "2.93", ""], ["臺灣優選成長高股息指數", "12,148.24", "<p style ='color:red'>+</p>", "313.65", "2.65", ""], ["特選臺灣ESG低碳高息40指數", "11,633.11", "<p style ='color:red'>+</p>", "281.58", "2.48", ""], ["臺灣優選多因子30指數", "14,433.95", "<p style ='color:red'>+</p>", "373.76", "2.66", ""], ["臺灣創新科技50指數", "22,498.09", "<p style ='color:red'>+</p>", "737.03", "3.39", ""], ["臺灣全市場新經濟產業指數", "3,992.33", "<p style ='color:green'>-</p>", "46.20", "-1.14", ""], ["臺灣ESG永續高股息等權重指數", "7,271.32", "<p style ='color:green'>-</p>", "23.99", "-0.33", ""], ["臺灣永續高息中小型指數", "7,512.41", "<p style ='color:red'>+</p>", "14.45", "0.19", ""], ["特選臺灣高息動能指數", "9,887.98", "<p style ='color:red'>+</p>", "183.77", "1.89", ""], ["臺灣電子成長高息等權重指數", "8,846.31", "<p style ='color:red'>+</p>", "166.55", "1.92", ""], ["特選臺灣優利成長指數", "7,376.66", "<p style ='color:red'>+</p>", "55.07", "0.75", ""], ["臺灣價值高息指數", "7,351.04", "<p style ='color:red'>+</p>", "121.53", "1.68", ""], ["特選臺灣IC設計動能指數", "13,493.51", "<p style ='color:red'>+</p>", "596.03", "4.62", ""], ["臺灣趨勢動能高股息指數", "8,445.30", "<p style ='color:red'>+</p>", "169.58", "2.05", ""], ["特選臺灣科技高息成長指數", "8,451.01", "<p style ='color:green'>-</p>", "24.91", "-0.29", ""], ["特選臺灣AI優息動能指數", "7,500.62", "<p style ='color:red'>+</p>", "126.82", "1.72", ""], ["臺灣優選AI 50指數", "9,298.01", "<p style ='color:red'>+</p>", "123.38", "1.34", ""], ["臺灣AI供應鏈聯盟指數", "17,328.14", "<p style ='color:red'>+</p>", "494.43", "2.94", ""], ["台灣旗艦動能50指數", "10,505.11", "<p style ='color:red'>+</p>", "282.00", "2.76", ""], ["特選臺灣動能趨勢指數", "16,606.68", "<p style ='color:red'>+</p>", "723.61", "4.56", ""]]}, {"title": "價格指數(臺灣指數公司)", "fields": ["指數", "收盤指數", "漲跌(+/-)", "漲跌點數", "漲跌百分比(%)", "特殊處理註記"], "data": [["金融類日報酬兩倍指數", "95,230.20", "<p style ='color:red'>+</p>", "4,973.78", "5.51", ""], ["金融類日報酬反向一倍指數", "2,272.88", "<p style ='color:green'>-</p>", "64.40", "-2.76", ""], ["漲升股利150指數", "21,606.70", "<p style ='color:red'>+</p>", "525.41", "2.49", ""], ["藍籌30指數", "27,772.00", "<p style ='color:red'>+</p>", "908.05", "3.38", ""], ["工業菁英30指數", "23,987.01", "<p style ='color:red'>+</p>", "681.18", "2.92", ""], ["低波動股利精選30指數", "12,373.04", "<p style ='color:red'>+</p>", "320.65", "2.66", ""], ["中小型A級動能50指數", "33,896.58", "<p style ='color:red'>+</p>", "1,360.20", "4.18", ""], ["特選高息低波指數", "11,925.85", "<p style ='color:red'>+</p>", "119.43", "1.01", ""], ["臺灣永續指數", "25,345.69", "<p style ='color:red'>+</p>", "706.65", "2.87", ""], ["存股雙十等權重指數", "20,898.33", "<p style ='color:red'>+</p>", "750.47", "3.72", ""], ["特選大蘋果指數", "30,870.43", "<p style ='color:red'>+</p>", "947.75", "3.17", ""], ["中小型300指數", "17,824.61", "<p style ='color:red'>+</p>", "336.93", "1.93", ""], ["微波高息精選20指數", "13,288.42", "<p style ='color:red'>+</p>", "344.00", "2.66", ""], ["特選世代行動通訊指數", "20,857.69", "<p style ='color:red'>+</p>", "695.42", "3.45", ""], ["智慧投資多因子30指數", "8,108.71", "<p style ='color:red'>+</p>", "20.43", "0.25", ""], ["臺股期貨指數", "24,952.79", "<p style ='color:red'>+</p>", "795.99", "3.30", ""], ["臺灣上櫃永續指數", "14,202.06", "<p style ='color:red'>+</p>", "300.54", "2.16", ""], ["特選台股領航指數", "26,360.73", "<p style ='color:red'>+</p>", "910.30", "3.58", ""], ["特選Smart多因子指數", "19,559.78", "<p style ='color:red'>+</p>", "495.44", "2.60", ""], ["特選ESG高股息指數", "13,048.78", "<p style ='color:red'>+</p>", "511.75", "4.08", ""], ["特選上櫃ESG成長指數", "10,236.70", "<p style ='color:red'>+</p>", "196.00", "1.95", ""], ["臺灣優息存股指數", "5,645.30", "<p style ='color:red'>+</p>", "47.65", "0.85", ""], ["特選上櫃ESG永續高股息指數", "15,238.01", "<p style ='color:red'>+</p>", "482.70", "3.27", ""], ["特選臺灣金融高股息存股指數", "9,867.50", "<p style ='color:red'>+</p>", "315.19", "3.30", ""], ["特選臺灣產業龍頭存股等權重指數", "9,009.46", "<p style ='color:red'>+</p>", "148.46", "1.68", ""], ["上櫃ESG 30指數", "16,121.06", "<p style ='color:red'>+</p>", "542.91", "3.49", ""], ["臺灣ESG低碳50指數", "17,092.03", "<p style ='color:red'>+</p>", "507.50", "3.06", ""], ["臺灣創新板指數", "18,786.27", "<p style ='color:red'>+</p>", "845.90", "4.72", ""], ["特選上櫃ESG龍頭指數", "14,026.81", "<p style ='color:red'>+</p>", "556.41", "4.13", ""], ["臺灣市值動能50指數", "11,050.83", "<p style ='color:red'>+</p>", "266.42", "2.47", ""], ["臺灣護城河概念優選50指數", "10,476.74", "<p style ='color:red'>+</p>", "298.46", "2.93", ""], ["特選臺灣中小型精選動能100指數", "7,156.88", "<p style ='color:red'>+</p>", "172.93", "2.48", ""], ["特選臺灣大型股25指數", "11,674.10", "<p style ='color:red'>+</p>", "347.79", "3.07", ""], ["特選臺灣TOP 50指數", "9,061.84", "<p style ='color:red'>+</p>", "274.93", "3.13", ""]]}, {"title": "報酬指數(臺灣證券交易所)", "fields": ["報酬指數", "收盤指數", "漲跌(+/-)", "漲跌點數", "漲跌百分比(%)", "特殊處理註記"], "data": [["寶島股價報酬指數", "77,889.17", "<p style ='color:red'>+</p>", "2,093.82", "2.76", ""], ["發行量加權股價報酬指數", "103,758.38", "<p style ='color:red'>+</p>", "2,824.91", "2.80", ""], ["臺灣公司治理100報酬指數", "42,721.61", "<p style ='color:red'>+</p>", "1,112.06", "2.67", ""], ["臺灣50報酬指數", "96,467.26", "<p style ='color:red'>+</p>", "2,823.51", "3.02", ""], ["臺灣50權重上限30%報酬指數", "83,227.48", "<p style ='color:red'>+</p>", "2,557.27", "3.17", ""], ["臺灣中型100報酬指數", "77,429.80", "<p style ='color:red'>+</p>", "1,676.74", "2.21", ""], ["臺灣資訊科技股報酬指數", "189,640.80", "<p style ='color:red'>+</p>", "5,896.07", "3.21", ""], ["臺灣發達報酬指數", "39,815.28", "<p style ='color:red'>+</p>", "488.62", "1.24", ""], ["臺灣高股息報酬指數", "46,043.46", "<p style ='color:red'>+</p>", "884.15", "1.96", ""], ["臺灣就業99報酬指數", "49,039.93", "<p style ='color:red'>+</p>", "1,621.80", "3.42", ""], ["臺灣高薪100報酬指數", "36,758.42", "<p style ='color:red'>+</p>", "890.28", "2.48", ""], ["未含金融電子報酬指數", "36,030.16", "<p style ='color:red'>+</p>", "479.21", "1.35", ""], ["小型股300報酬指數", "21,311.10", "<p style ='color:red'>+</p>", "414.64", "1.98", ""], ["水泥類報酬指數", "277.77", "<p style ='color:red'>+</p>", "2.65", "0.96", ""], ["食品類報酬指數", "3,407.54", "<p style ='color:green'>-</p>", "5.39", "-0.16", ""], ["塑膠類報酬指數", "456.34", "<p style ='color:red'>+</p>", "30.27", "7.10", ""], ["紡織纖維類報酬指數", "897.63", "<p style ='color:red'>+</p>", "2.98", "0.33", ""], ["電機機械類報酬指數", "890.20", "<p style ='color:red'>+</p>", "17.35", "1.99", ""], ["電器電纜類報酬指數", "194.57", "<p style ='color:red'>+</p>", "7.46", "3.99", ""], ["化學生技醫療類報酬指數", "254.35", "<p style ='color:red'>+</p>", "2.85", "1.13", ""], ["化學類報酬指數", "372.05", "<p style ='color:red'>+</p>", "4.98", "1.36", ""], ["生技醫療類報酬指數", "119.38", "<p style ='color:red'>+</p>", "1.21", "1.02", ""], ["玻璃陶瓷類報酬指數", "203.67", "<p style ='color:red'>+</p>", "9.58", "4.94", ""], ["造紙類報酬指數", "433.98", "<p style ='color:red'>+</p>", "2.25", "0.52", ""], ["鋼鐵類報酬指數", "222.33", "<p style ='color:red'>+</p>", "1.31", "0.59", ""], ["橡膠類報酬指數", "359.49", "<p style ='color:green'>-</p>", "1.06", "-0.29", ""], ["汽車類報酬指數", "526.29", "<p style ='color:red'>+</p>", "9.18", "1.78", ""], ["電子工業類報酬指數", "6,014.45", "<p style ='color:red'>+</p>", "174.25", "2.98", ""], ["半導體類報酬指數", "2,938.44", "<p style ='color:red'>+</p>", "94.04", "3.31", ""], ["電腦及週邊設備類報酬指數", "1,004.86", "<p style ='color:red'>+</p>", "3.78", "0.38", ""], ["光電類報酬指數", "109.46", "<p style ='color:red'>+</p>", "5.53", "5.32", ""], ["通信網路類報酬指數", "598.57", "<p style ='color:red'>+</p>", "11.81", "2.01", ""], ["電子零組件類報酬指數", "1,993.27", "<p style ='color:red'>+</p>", "58.93", "3.05", ""], ["電子通路類報酬指數", "1,069.87", "<p style ='color:red'>+</p>", "5.07", "0.48", ""], ["資訊服務類報酬指數", "564.70", "<p style ='color:green'>-</p>", "1.81", "-0.32", ""], ["其他電子類報酬指數", "532.92", "<p style ='color:red'>+</p>", "10.74", "2.06", ""], ["建材營造類報酬指數", "1,090.02", "<p style ='color:red'>+</p>", "6.43", "0.59", ""], ["航運類報酬指數", "411.75", "<p style ='color:red'>+</p>", "0.54", "0.13", ""], ["觀光餐旅類報酬指數", "161.45", "<p style ='color:red'>+</p>", "0.11", "0.07", ""], ["金融保險類報酬指數", "5,902.94", "<p style ='color:red'>+</p>", "158.75", "2.76", ""], ["貿易百貨類報酬指數", "416.13", "<p style ='color:red'>+</p>", "2.21", "0.53", ""], ["油電燃氣類報酬指數", "131.86", "<p style ='color:red'>+</p>", "0.72", "0.55", ""], ["綠能環保類報酬指數", "148.10", "<p style ='color:red'>+</p>", "3.14", "2.17", ""], ["數位雲端類報酬指數", "52.46", "<p style ='color:green'>-</p>", "3.32", "-5.95", ""], ["運動休閒類報酬指數", "69.69", "<p style ='color:green'>-</p>", "2.28", "-3.17", ""], ["居家生活類報酬指數", "111.70", "<p style ='color:green'>-</p>", "1.06", "-0.94", ""], ["其他類報酬指數", "534.45", "<p style ='color:green'>-</p>", "3.17", "-0.59", ""]]}, {"title": "報酬指數(跨市場)", "fields": ["報酬指數", "收盤指數", "漲跌(+/-)", "漲跌點數", "漲跌百分比(%)", "特殊處理註記"], "data": [["臺灣生技報酬指數", "4,227.16", "<p style ='color:red'>+</p>", "32.89", "0.78", ""], ["臺灣中小型公司治理報酬指數", "30,013.85", "<p style ='color:red'>+</p>", "178.06", "0.60", ""], ["臺灣IPO報酬指數", "11,590.78", "<p style ='color:red'>+</p>", "129.06", "1.13", ""], ["智慧中立報酬指數", "4,349.48", "<p style ='color:green'>-</p>", "7.23", "-0.17", ""], ["加權指數掩護性臺指買權價外5%報酬指數", "16,287.08", "<p style ='color:red'>+</p>", "18.80", "0.12", ""], ["臺灣企業社會責任中小型報酬指數", "22,635.31", "<p style ='color:red'>+</p>", "375.12", "1.69", ""], ["特選臺灣電動車代表報酬指數", "26,526.86", "<p style ='color:red'>+</p>", "170.96", "0.65", ""], ["臺灣科技龍頭通訊報酬指數", "30,763.22", "<p style ='color:red'>+</p>", "877.72", "2.94", ""], ["臺灣全市場報酬指數", "18,790.24", "<p style ='color:red'>+</p>", "518.61", "2.84", ""], ["臺灣全市場半導體報酬指數", "24,752.50", "<p style ='color:red'>+</p>", "933.30", "3.92", ""], ["臺灣智慧移動與電動車報酬指數", "20,260.54", "<p style ='color:red'>+</p>", "757.50", "3.88", ""], ["特選小資高價30報酬指數", "25,700.66", "<p style ='color:red'>+</p>", "704.74", "2.82", ""], ["特選臺灣綠能及電動車報酬指數", "13,979.18", "<p style ='color:red'>+</p>", "292.29", "2.14", ""], ["特選臺灣智能車供應鏈聯盟報酬指數", "21,752.76", "<p style ='color:red'>+</p>", "667.84", "3.17", ""], ["臺灣全市場半導體精選30報酬指數", "18,950.91", "<p style ='color:red'>+</p>", "658.61", "3.60", ""], ["特選臺灣高股息30報酬指數", "10,895.08", "<p style ='color:red'>+</p>", "211.64", "1.98", ""], ["臺灣友善環境報酬指數", "15,699.26", "<p style ='color:red'>+</p>", "376.87", "2.46", ""], ["台灣永續價值報酬指數", "15,217.66", "<p style ='color:red'>+</p>", "363.67", "2.45", ""], ["特選臺灣IC設計報酬指數", "9,290.61", "<p style ='color:red'>+</p>", "295.73", "3.29", ""], ["特選臺灣環境永續高股息報酬指數", "12,150.81", "<p style ='color:red'>+</p>", "219.89", "1.84", ""], ["臺灣友善環境50報酬指數", "14,795.93", "<p style ='color:red'>+</p>", "424.29", "2.95", ""], ["特選臺灣IC設計產業代表報酬指數", "12,405.24", "<p style ='color:red'>+</p>", "428.79", "3.58", ""], ["特選臺灣綠能報酬指數", "11,378.95", "<p style ='color:red'>+</p>", "72.51", "0.64", ""], ["特選臺灣智慧50報酬指數", "12,552.04", "<p style ='color:red'>+</p>", "288.33", "2.35", ""], ["臺灣晶圓製造報酬指數", "19,958.33", "<p style ='color:red'>+</p>", "837.74", "4.38", ""], ["臺灣精選高息報酬指數", "11,841.20", "<p style ='color:red'>+</p>", "194.71", "1.67", ""], ["臺灣多因子優選高股息30報酬指數", "14,290.78", "<p style ='color:red'>+</p>", "347.73", "2.49", ""], ["特選臺灣優利高填息30報酬指數", "15,320.35", "<p style ='color:red'>+</p>", "520.22", "3.51", ""], ["特選臺灣科技優息報酬指數", "18,097.01", "<p style ='color:red'>+</p>", "585.72", "3.34", ""], ["臺灣半導體收益報酬指數", "18,792.90", "<p style ='color:red'>+</p>", "544.64", "2.98", ""], ["臺灣優選成長高股息報酬指數", "14,192.94", "<p style ='color:red'>+</p>", "368.97", "2.67", ""], ["特選臺灣ESG低碳高息40報酬指數", "13,599.28", "<p style ='color:red'>+</p>", "357.28", "2.70", ""], ["臺灣優選多因子30報酬指數", "16,036.83", "<p style ='color:red'>+</p>", "422.94", "2.71", ""], ["臺灣創新科技50報酬指數", "24,835.93", "<p style ='color:red'>+</p>", "813.62", "3.39", ""], ["臺灣全市場新經濟產業報酬指數", "4,489.59", "<p style ='color:green'>-</p>", "37.85", "-0.84", ""], ["臺灣ESG永續高股息等權重報酬指數", "8,449.82", "<p style ='color:red'>+</p>", "6.09", "0.07", ""], ["臺灣永續高息中小型報酬指數", "8,511.20", "<p style ='color:red'>+</p>", "51.33", "0.61", ""], ["特選臺灣高息動能報酬指數", "11,018.11", "<p style ='color:red'>+</p>", "207.51", "1.92", ""], ["臺灣電子成長高息等權重報酬指數", "9,820.35", "<p style ='color:red'>+</p>", "207.65", "2.16", ""], ["特選臺灣優利成長報酬指數", "8,274.55", "<p style ='color:red'>+</p>", "86.70", "1.06", ""], ["臺灣價值高息報酬指數", "8,242.98", "<p style ='color:red'>+</p>", "159.57", "1.97", ""], ["特選臺灣IC設計動能報酬指數", "14,200.00", "<p style ='color:red'>+</p>", "629.08", "4.64", ""], ["臺灣趨勢動能高股息報酬指數", "9,431.51", "<p style ='color:red'>+</p>", "204.65", "2.22", ""], ["特選臺灣科技高息成長報酬指數", "9,441.88", "<p style ='color:red'>+</p>", "22.44", "0.24", ""], ["特選臺灣AI優息動能報酬指數", "8,082.05", "<p style ='color:red'>+</p>", "136.65", "1.72", ""], ["臺灣優選AI 50報酬指數", "10,046.90", "<p style ='color:red'>+</p>", "149.77", "1.51", ""], ["臺灣AI供應鏈聯盟報酬指數", "17,887.98", "<p style ='color:red'>+</p>", "510.41", "2.94", ""], ["台灣旗艦動能50報酬指數", "11,080.97", "<p style ='color:red'>+</p>", "306.02", "2.84", ""], ["特選臺灣動能趨勢報酬指數", "17,820.50", "<p style ='color:red'>+</p>", "776.50", "4.56", ""]]}, {"title": "報酬指數(臺灣指數公司)", "fields": ["報酬指數", "收盤指數", "漲跌(+/-)", "漲跌點數", "漲跌百分比(%)", "特殊處理註記"], "data": [["漲升股利150報酬指數", "33,309.83", "<p style ='color:red'>+</p>", "840.68", "2.59", ""], ["藍籌30報酬指數", "39,340.50", "<p style ='color:red'>+</p>", "1,286.30", "3.38", ""], ["工業菁英30報酬指數", "34,395.12", "<p style ='color:red'>+</p>", "976.75", "2.92", ""], ["低波動股利精選30報酬指數", "17,924.82", "<p style ='color:red'>+</p>", "464.52", "2.66", ""], ["中小型A級動能50報酬指數", "44,617.81", "<p style ='color:red'>+</p>", "1,790.42", "4.18", ""], ["特選高息低波報酬指數", "19,222.28", "<p style ='color:red'>+</p>", "211.87", "1.11", ""], ["臺灣永續報酬指數", "35,852.80", "<p style ='color:red'>+</p>", "1,007.09", "2.89", ""], ["存股雙十等權重報酬指數", "30,862.97", "<p style ='color:red'>+</p>", "1,167.10", "3.93", ""], ["特選大蘋果報酬指數", "41,387.02", "<p style ='color:red'>+</p>", "1,270.62", "3.17", ""], ["中小型300報酬指數", "23,019.24", "<p style ='color:red'>+</p>", "456.81", "2.02", ""], ["微波高息精選20報酬指數", "17,744.59", "<p style ='color:red'>+</p>", "491.52", "2.85", ""], ["特選世代行動通訊報酬指數", "26,324.18", "<p style ='color:red'>+</p>", "877.68", "3.45", ""], ["智慧投資多因子30報酬指數", "11,120.95", "<p style ='color:red'>+</p>", "42.17", "0.38", ""], ["特選大蘋果報酬正向兩倍指數", "263,085.36", "<p style ='color:red'>+</p>", "15,672.76", "6.33", ""], ["特選大蘋果報酬反向一倍指數", "1,030.20", "<p style ='color:green'>-</p>", "33.70", "-3.17", ""], ["臺灣上櫃永續報酬指數", "17,721.99", "<p style ='color:red'>+</p>", "375.72", "2.17", ""], ["特選台股領航報酬指數", "34,246.79", "<p style ='color:red'>+</p>", "1,182.62", "3.58", ""], ["特選Smart多因子報酬指數", "24,004.85", "<p style ='color:red'>+</p>", "613.02", "2.62", ""], ["特選ESG高股息報酬指數", "18,252.38", "<p style ='color:red'>+</p>", "724.97", "4.14", ""], ["特選上櫃ESG成長報酬指數", "11,895.75", "<p style ='color:red'>+</p>", "227.76", "1.95", ""], ["臺灣優息存股報酬指數", "7,062.85", "<p style ='color:red'>+</p>", "66.76", "0.95", ""], ["特選上櫃ESG永續高股息報酬指數", "18,057.06", "<p style ='color:red'>+</p>", "572.01", "3.27", ""], ["特選臺灣金融高股息存股報酬指數", "11,376.08", "<p style ='color:red'>+</p>", "363.37", "3.30", ""], ["特選臺灣產業龍頭存股等權重報酬指數", "10,354.90", "<p style ='color:red'>+</p>", "178.47", "1.75", ""], ["上櫃ESG 30報酬指數", "17,896.03", "<p style ='color:red'>+</p>", "602.69", "3.49", ""], ["臺灣ESG低碳50報酬指數", "19,100.13", "<p style ='color:red'>+</p>", "567.12", "3.06", ""], ["臺灣創新板報酬指數", "19,342.86", "<p style ='color:red'>+</p>", "870.96", "4.72", ""], ["特選上櫃ESG龍頭報酬指數", "15,191.68", "<p style ='color:red'>+</p>", "602.62", "4.13", ""], ["臺灣市值動能50報酬指數", "11,556.87", "<p style ='color:red'>+</p>", "278.62", "2.47", ""], ["臺灣護城河概念優選50報酬指數", "10,896.65", "<p style ='color:red'>+</p>", "312.26", "2.95", ""], ["特選臺灣中小型精選動能100報酬指數", "7,432.11", "<p style ='color:red'>+</p>", "179.63", "2.48", ""], ["特選臺灣大型股25報酬指數", "12,039.32", "<p style ='color:red'>+</p>", "358.67", "3.07", ""], ["特選臺灣TOP 50報酬指數", "9,107.04", "<p style ='color:red'>+</p>", "276.30", "3.13", ""]]}, {}, {}, {}, {}], "type": "IND", "params": {"date": "20260615", "type": "IND", "response": "json", "controller": "afterTrading", "action": "MI_INDEX", "lang": "zh"}, "stat": "OK", "notes": ["\"漲跌價差\"為當日收盤價與前一日收盤價比較。", "\"無比價\"含前一日無收盤價、當日除權、除息、新上市、恢復交易者。", "外幣成交值係以本公司當日下午3時30分公告匯率換算後加入成交金額。公告匯率請參考本公司首頁>產品與服務>交易系統>雙幣ETF專區>代號對應及每日公告匯率。", "特殊處理註記說明如下：<br>(1)A:指數公司重新計算指數收盤點數。(2)B:依據編製規則，採商品(指數)非收盤價(點數)計算指數收盤點數。(3)空白:無特殊處理。(4)有關A、B兩種特殊處理註記，其原因及說明請至<a href= 'https://www.taiwanindex.com.tw/' target='_blank'>臺灣指數公司網站</a>查閱相關指數編製規則。", "本公司提供部分臺灣指數公司的收盤指數資訊,欲查閱完整內容,請至<a href= 'https://www.taiwanindex.com.tw/' target='_blank'>臺灣指數公司網站</a>進行查詢。"], "date": "20260615"}